{
"_generated": "2026-06-09",
"data": {
"SPY": {
"marketCap": null,
"trailingPE": 26.39705,
"forwardPE": null,
"pegRatio": null,
"priceToBook": 1.7171847,
"enterpriseToEbitda": null,
"revenueGrowth": null,
"earningsGrowth": null,
"earningsQuarterlyGrowth": null,
"grossMargins": null,
"operatingMargins": null,
"profitMargins": null,
"returnOnEquity": null,
"returnOnAssets": null,
"debtToEquity": null,
"currentRatio": null,
"quickRatio": null,
"freeCashflow": null,
"totalCash": null,
"totalDebt": null,
"dividendYield": 0.0098,
"payoutRatio": null,
"beta": null,
"targetMeanPrice": null,
"targetHighPrice": null,
"targetLowPrice": null,
"recommendationKey": null,
"numberOfAnalystOpinions": null
},
"QQQ": {
"marketCap": null,
"trailingPE": 31.588682,
"forwardPE": null,
"pegRatio": null,
"priceToBook": 1.9784279,
"enterpriseToEbitda": null,
"revenueGrowth": null,
"earningsGrowth": null,
"earningsQuarterlyGrowth": null,
"grossMargins": null,
"operatingMargins": null,
"profitMargins": null,
"returnOnEquity": null,
"returnOnAssets": null,
"debtToEquity": null,
"currentRatio": null,
"quickRatio": null,
"freeCashflow": null,
"totalCash": null,
"totalDebt": null,
"dividendYield": 0.0038,
"payoutRatio": null,
"beta": null,
"targetMeanPrice": null,
"targetHighPrice": null,
"targetLowPrice": null,
"recommendationKey": null,
"numberOfAnalystOpinions": null
},
"XLK": {
"marketCap": null,
"trailingPE": 36.02363,
"forwardPE": null,
"pegRatio": null,
"priceToBook": 1.2103379,
"enterpriseToEbitda": null,
"revenueGrowth": null,
"earningsGrowth": null,
"earningsQuarterlyGrowth": null,
"grossMargins": null,
"operatingMargins": null,
"profitMargins": null,
"returnOnEquity": null,
"returnOnAssets": null,
"debtToEquity": null,
"currentRatio": null,
"quickRatio": null,
"freeCashflow": null,
"totalCash": null,
"totalDebt": null,
"dividendYield": 0.004,
"payoutRatio": null,
"beta": null,
"targetMeanPrice": null,
"targetHighPrice": null,
"targetLowPrice": null,
"recommendationKey": null,
"numberOfAnalystOpinions": null
},
"SMH": {
"marketCap": null,
"trailingPE": 39.853653,
"forwardPE": null,
"pegRatio": null,
"priceToBook": null,
"enterpriseToEbitda": null,
"revenueGrowth": null,
"earningsGrowth": null,
"earningsQuarterlyGrowth": null,
"grossMargins": null,
"operatingMargins": null,
"profitMargins": null,
"returnOnEquity": null,
"returnOnAssets": null,
"debtToEquity": null,
"currentRatio": null,
"quickRatio": null,
"freeCashflow": null,
"totalCash": null,
"totalDebt": null,
"dividendYield": 0.0018,
"payoutRatio": null,
"beta": null,
"targetMeanPrice": null,
"targetHighPrice": null,
"targetLowPrice": null,
"recommendationKey": null,
"numberOfAnalystOpinions": null
},
"NVDA": {
"marketCap": 5042570002432,
"trailingPE": 31.882082,
"forwardPE": 16.415857,
"pegRatio": 0.63,
"priceToBook": 32.1678,
"enterpriseToEbitda": 30.262,
"revenueGrowth": 0.852,
"earningsGrowth": 2.145,
"earningsQuarterlyGrowth": 2.106,
"grossMargins": 0.74144995,
"operatingMargins": 0.65596,
"profitMargins": 0.62966,
"returnOnEquity": 1.14288,
"returnOnAssets": 0.52727,
"debtToEquity": 6.555,
"currentRatio": 3.441,
"quickRatio": 2.139,
"freeCashflow": 46335873024,
"totalCash": 53171998720,
"totalDebt": 12814000128,
"dividendYield": 0.0048,
"payoutRatio": 0.0061000003,
"beta": 2.202,
"targetMeanPrice": 298.42374,
"targetHighPrice": 500.0,
"targetLowPrice": 180.0,
"recommendationKey": "strong_buy",
"numberOfAnalystOpinions": 59
},
"AAPL": {
"marketCap": 4267410980864,
"trailingPE": 35.17554,
"forwardPE": 30.234224,
"pegRatio": 2.47,
"priceToBook": 40.020657,
"enterpriseToEbitda": 27.786,
"revenueGrowth": 0.166,
"earningsGrowth": 0.218,
"earningsQuarterlyGrowth": 0.194,
"grossMargins": 0.47862,
"operatingMargins": 0.32275,
"profitMargins": 0.27152002,
"returnOnEquity": 1.4147099,
"returnOnAssets": 0.26229,
"debtToEquity": 79.548,
"currentRatio": 1.07,
"quickRatio": 0.906,
"freeCashflow": 101090746368,
"totalCash": 68507000832,
"totalDebt": 84710998016,
"dividendYield": 0.0036,
"payoutRatio": 0.1259,
"beta": 1.086,
"targetMeanPrice": 310.507,
"targetHighPrice": 400.0,
"targetLowPrice": 215.0,
"recommendationKey": "buy",
"numberOfAnalystOpinions": 43
},
"MSFT": {
"marketCap": 2996704903168,
"trailingPE": 24.0125,
"forwardPE": 20.856276,
"pegRatio": 1.28,
"priceToBook": 7.232551,
"enterpriseToEbitda": 16.837,
"revenueGrowth": 0.183,
"earningsGrowth": 0.234,
"earningsQuarterlyGrowth": 0.231,
"grossMargins": 0.68309,
"operatingMargins": 0.46326,
"profitMargins": 0.39341998,
"returnOnEquity": 0.34013999,
"returnOnAssets": 0.14814,
"debtToEquity": 30.271,
"currentRatio": 1.283,
"quickRatio": 1.142,
"freeCashflow": 37011251200,
"totalCash": 78227996672,
"totalDebt": 125431996416,
"dividendYield": 0.0088,
"payoutRatio": 0.20729999,
"beta": 1.103,
"targetMeanPrice": 560.946,
"targetHighPrice": 870.0,
"targetLowPrice": 400.0,
"recommendationKey": "strong_buy",
"numberOfAnalystOpinions": 55
},
"GOOGL": {
"marketCap": 4442127073280,
"trailingPE": 27.76372,
"forwardPE": 25.18112,
"pegRatio": 1.43,
"priceToBook": 9.218505,
"enterpriseToEbitda": 27.095,
"revenueGrowth": 0.218,
"earningsGrowth": 0.82,
"earningsQuarterlyGrowth": 0.812,
"grossMargins": 0.60368,
"operatingMargins": 0.36121,
"profitMargins": 0.37919,
"returnOnEquity": 0.38884997,
"returnOnAssets": 0.14641,
"debtToEquity": 20.026,
"currentRatio": 1.922,
"quickRatio": 1.707,
"freeCashflow": 27921750016,
"totalCash": 126839996416,
"totalDebt": 95875997696,
"dividendYield": 0.0024,
"payoutRatio": 0.0641,
"beta": 1.237,
"targetMeanPrice": 431.75906,
"targetHighPrice": 515.0,
"targetLowPrice": 340.0,
"recommendationKey": "strong_buy",
"numberOfAnalystOpinions": 53
},
"AMZN": {
"marketCap": 2626778562560,
"trailingPE": 31.508387,
"forwardPE": 24.765821,
"pegRatio": 1.83,
"priceToBook": 5.9423747,
"enterpriseToEbitda": 17.518,
"revenueGrowth": 0.166,
"earningsGrowth": 0.748,
"earningsQuarterlyGrowth": 0.767,
"grossMargins": 0.50604,
"operatingMargins": 0.1314,
"profitMargins": 0.12224,
"returnOnEquity": 0.24285,
"returnOnAssets": 0.06845,
"debtToEquity": 53.3,
"currentRatio": 1.177,
"quickRatio": 0.974,
"freeCashflow": 9806624768,
"totalCash": 143088992256,
"totalDebt": 235540004864,
"dividendYield": null,
"payoutRatio": 0.0,
"beta": 1.444,
"targetMeanPrice": 312.7934,
"targetHighPrice": 370.0,
"targetLowPrice": 207.0,
"recommendationKey": "strong_buy",
"numberOfAnalystOpinions": 62
},
"META": {
"marketCap": 1483936890880,
"trailingPE": 21.250092,
"forwardPE": 16.165812,
"pegRatio": 0.86,
"priceToBook": 6.088655,
"enterpriseToEbitda": 13.645,
"revenueGrowth": 0.331,
"earningsGrowth": 0.624,
"earningsQuarterlyGrowth": 0.609,
"grossMargins": 0.81941,
"operatingMargins": 0.40617,
"profitMargins": 0.32837,
"returnOnEquity": 0.32930002,
"returnOnAssets": 0.16395001,
"debtToEquity": 35.608,
"currentRatio": 2.348,
"quickRatio": 2.11,
"freeCashflow": 25558249472,
"totalCash": 81180000256,
"totalDebt": 86769000448,
"dividendYield": 0.0036,
"payoutRatio": 0.0764,
"beta": 1.229,
"targetMeanPrice": 828.798,
"targetHighPrice": 1015.0,
"targetLowPrice": 700.0,
"recommendationKey": "strong_buy",
"numberOfAnalystOpinions": 59
},
"TSLA": {
"marketCap": 1489820450816,
"trailingPE": 360.61816,
"forwardPE": 157.87505,
"pegRatio": 5.38,
"priceToBook": 18.115725,
"enterpriseToEbitda": 135.906,
"revenueGrowth": 0.158,
"earningsGrowth": 0.083,
"earningsQuarterlyGrowth": 0.166,
"grossMargins": 0.19065,
"operatingMargins": 0.04203,
"profitMargins": 0.03946,
"returnOnEquity": 0.04901,
"returnOnAssets": 0.022330001,
"debtToEquity": 18.738,
"currentRatio": 2.043,
"quickRatio": 1.43,
"freeCashflow": 5251999744,
"totalCash": 44743000064,
"totalDebt": 15889999872,
"dividendYield": null,
"payoutRatio": 0.0,
"beta": 1.798,
"targetMeanPrice": 419.93658,
"targetHighPrice": 600.0,
"targetLowPrice": 123.0,
"recommendationKey": "buy",
"numberOfAnalystOpinions": 41
},
"AVGO": {
"marketCap": 1856747470848,
"trailingPE": 65.03482,
"forwardPE": 20.266624,
"pegRatio": 0.71,
"priceToBook": 21.22882,
"enterpriseToEbitda": 45.96,
"revenueGrowth": 0.479,
"earningsGrowth": 0.854,
"earningsQuarterlyGrowth": 0.875,
"grossMargins": 0.76284,
"operatingMargins": 0.48988,
"profitMargins": 0.38848,
"returnOnEquity": 0.37280998,
"returnOnAssets": 0.121190004,
"debtToEquity": 74.018,
"currentRatio": 2.238,
"quickRatio": 1.615,
"freeCashflow": 27212249088,
"totalCash": 19627999232,
"totalDebt": 64907001856,
"dividendYield": 0.0066,
"payoutRatio": 0.41259998,
"beta": 1.433,
"targetMeanPrice": 517.6067,
"targetHighPrice": 650.0,
"targetLowPrice": 215.88,
"recommendationKey": "strong_buy",
"numberOfAnalystOpinions": 45
},
"AMD": {
"marketCap": 775358709760,
"trailingPE": 159.03177,
"forwardPE": 36.363018,
"pegRatio": 1.12,
"priceToBook": 12.023794,
"enterpriseToEbitda": 106.468,
"revenueGrowth": 0.378,
"earningsGrowth": 0.912,
"earningsQuarterlyGrowth": 0.951,
"grossMargins": 0.5306,
"operatingMargins": 0.14396,
"profitMargins": 0.13374,
"returnOnEquity": 0.08063,
"returnOnAssets": 0.03647,
"debtToEquity": 6.005,
"currentRatio": 2.725,
"quickRatio": 1.75,
"freeCashflow": 7173374976,
"totalCash": 12346999808,
"totalDebt": 3871000064,
"dividendYield": null,
"payoutRatio": 0.0,
"beta": 2.492,
"targetMeanPrice": 482.6875,
"targetHighPrice": 665.0,
"targetLowPrice": 225.0,
"recommendationKey": "strong_buy",
"numberOfAnalystOpinions": 48
},
"TSM": {
"marketCap": 2219396038656,
"trailingPE": 36.731335,
"forwardPE": 21.912165,
"pegRatio": 1.29,
"priceToBook": 65.45768,
"enterpriseToEbitda": 5.413,
"revenueGrowth": 0.351,
"earningsGrowth": 0.584,
"earningsQuarterlyGrowth": 0.583,
"grossMargins": 0.61873,
"operatingMargins": 0.58105,
"profitMargins": 0.46505,
"returnOnEquity": 0.3621,
"returnOnAssets": 0.17322001,
"debtToEquity": 18.447,
"currentRatio": 2.488,
"quickRatio": 2.187,
"freeCashflow": 719158444032,
"totalCash": 3383596154880,
"totalDebt": 1094369804288,
"dividendYield": 0.0089,
"payoutRatio": 0.2793,
"beta": 1.25,
"targetMeanPrice": 467.84027,
"targetHighPrice": 600.0,
"targetLowPrice": 354.0,
"recommendationKey": "strong_buy",
"numberOfAnalystOpinions": 18
},
"CRM": {
"marketCap": 143611658240,
"trailingPE": 20.318657,
"forwardPE": 11.283349,
"pegRatio": 0.9,
"priceToBook": 4.194876,
"enterpriseToEbitda": 13.976,
"revenueGrowth": 0.133,
"earningsGrowth": 0.522,
"earningsQuarterlyGrowth": 0.367,
"grossMargins": 0.77643996,
"operatingMargins": 0.218,
"profitMargins": 0.18733,
"returnOnEquity": 0.16908,
"returnOnAssets": 0.05703,
"debtToEquity": 124.282,
"currentRatio": 0.786,
"quickRatio": 0.615,
"freeCashflow": 16552999936,
"totalCash": 11836999680,
"totalDebt": 42547998720,
"dividendYield": 0.0096,
"payoutRatio": 0.19559999,
"beta": 1.151,
"targetMeanPrice": 254.98906,
"targetHighPrice": 475.0,
"targetLowPrice": 160.0,
"recommendationKey": "buy",
"numberOfAnalystOpinions": 53
},
"GOOG": {
"marketCap": 4418103148544,
"trailingPE": 27.634632,
"forwardPE": 25.044935,
"pegRatio": 1.42,
"priceToBook": 9.16865,
"enterpriseToEbitda": 26.935,
"revenueGrowth": 0.218,
"earningsGrowth": 0.82,
"earningsQuarterlyGrowth": 0.812,
"grossMargins": 0.60368,
"operatingMargins": 0.36121,
"profitMargins": 0.37919,
"returnOnEquity": 0.38884997,
"returnOnAssets": 0.14641,
"debtToEquity": 20.026,
"currentRatio": 1.922,
"quickRatio": 1.707,
"freeCashflow": 27921750016,
"totalCash": 126839996416,
"totalDebt": 95875997696,
"dividendYield": 0.0024,
"payoutRatio": 0.0641,
"beta": 1.237,
"targetMeanPrice": 409.00287,
"targetHighPrice": 475.0,
"targetLowPrice": 195.0,
"recommendationKey": "strong_buy",
"numberOfAnalystOpinions": 14
},
"NFLX": {
"marketCap": 342801121280,
"trailingPE": 26.261292,
"forwardPE": 21.192244,
"pegRatio": 1.61,
"priceToBook": 11.01773,
"enterpriseToEbitda": 24.677,
"revenueGrowth": 0.162,
"earningsGrowth": 0.864,
"earningsQuarterlyGrowth": 0.828,
"grossMargins": 0.49029,
"operatingMargins": 0.32303002,
"profitMargins": 0.28521,
"returnOnEquity": 0.48494998,
"returnOnAssets": 0.15402001,
"debtToEquity": 53.788,
"currentRatio": 1.407,
"quickRatio": 1.178,
"freeCashflow": 25993676800,
"totalCash": 12288449536,
"totalDebt": 16742200320,
"dividendYield": null,
"payoutRatio": 0.0,
"beta": 1.491,
"targetMeanPrice": 114.555,
"targetHighPrice": 151.4,
"targetLowPrice": 80.0,
"recommendationKey": "buy",
"numberOfAnalystOpinions": 44
},
"INTC": {
"marketCap": 542405885952,
"trailingPE": null,
"forwardPE": 70.10296,
"pegRatio": 1.36,
"priceToBook": 4.866303,
"enterpriseToEbitda": 40.924,
"revenueGrowth": 0.072,
"earningsGrowth": null,
"earningsQuarterlyGrowth": null,
"grossMargins": 0.372,
"operatingMargins": 0.06879,
"profitMargins": -0.05904,
"returnOnEquity": -0.02911,
"returnOnAssets": 0.0063099996,
"debtToEquity": 36.028,
"currentRatio": 2.312,
"quickRatio": 1.657,
"freeCashflow": -8301250048,
"totalCash": 32789000192,
"totalDebt": 45030998016,
"dividendYield": null,
"payoutRatio": 0.0,
"beta": 2.228,
"targetMeanPrice": 89.32195,
"targetHighPrice": 150.0,
"targetLowPrice": 20.4,
"recommendationKey": "hold",
"numberOfAnalystOpinions": 41
},
"QCOM": {
"marketCap": 216512675840,
"trailingPE": 22.088171,
"forwardPE": 19.257235,
"pegRatio": 0.91,
"priceToBook": 7.974998,
"enterpriseToEbitda": 18.078,
"revenueGrowth": -0.035,
"earningsGrowth": 1.73,
"earningsQuarterlyGrowth": 1.621,
"grossMargins": 0.54799,
"operatingMargins": 0.22059,
"profitMargins": 0.22308001,
"returnOnEquity": 0.36083,
"returnOnAssets": 0.12692,
"debtToEquity": 55.979,
"currentRatio": 2.366,
"quickRatio": 1.448,
"freeCashflow": 9589624832,
"totalCash": 9799000064,
"totalDebt": 15269999616,
"dividendYield": 0.0169,
"payoutRatio": 0.38279998,
"beta": 1.596,
"targetMeanPrice": 180.48387,
"targetHighPrice": 300.0,
"targetLowPrice": 100.0,
"recommendationKey": "hold",
"numberOfAnalystOpinions": 31
},
"TXN": {
"marketCap": 262680084480,
"trailingPE": 49.338463,
"forwardPE": 30.660925,
"pegRatio": 1.36,
"priceToBook": 15.654933,
"enterpriseToEbitda": 31.586,
"revenueGrowth": 0.186,
"earningsGrowth": 0.313,
"earningsQuarterlyGrowth": 0.31,
"grossMargins": 0.57322,
"operatingMargins": 0.37824002,
"profitMargins": 0.29108,
"returnOnEquity": 0.32347,
"returnOnAssets": 0.12161,
"debtToEquity": 83.741,
"currentRatio": 4.456,
"quickRatio": 2.827,
"freeCashflow": 1068249984,
"totalCash": 5103000064,
"totalDebt": 14049999872,
"dividendYield": 0.0195,
"payoutRatio": 0.9504,
"beta": 1.309,
"targetMeanPrice": 290.33334,
"targetHighPrice": 400.0,
"targetLowPrice": 200.0,
"recommendationKey": "buy",
"numberOfAnalystOpinions": 33
},
"MU": {
"marketCap": 1055434997760,
"trailingPE": 44.208313,
"forwardPE": 8.552857,
"pegRatio": 0.3,
"priceToBook": 14.569329,
"enterpriseToEbitda": 28.985,
"revenueGrowth": 1.963,
"earningsGrowth": 7.56,
"earningsQuarterlyGrowth": 7.708,
"grossMargins": 0.58437,
"operatingMargins": 0.67624,
"profitMargins": 0.41486,
"returnOnEquity": 0.39823002,
"returnOnAssets": 0.20145,
"debtToEquity": 14.902,
"currentRatio": 2.897,
"quickRatio": 2.232,
"freeCashflow": 2893499904,
"totalCash": 14588999680,
"totalDebt": 10798000128,
"dividendYield": 0.06,
"payoutRatio": 0.0217,
"beta": 2.173,
"targetMeanPrice": 739.475,
"targetHighPrice": 1750.0,
"targetLowPrice": 249.0,
"recommendationKey": "strong_buy",
"numberOfAnalystOpinions": 40
},
"ORCL": {
"marketCap": 591919054848,
"trailingPE": 36.94973,
"forwardPE": 25.558014,
"pegRatio": 1.35,
"priceToBook": 17.641865,
"enterpriseToEbitda": 26.885,
"revenueGrowth": 0.217,
"earningsGrowth": 0.245,
"earningsQuarterlyGrowth": 0.267,
"grossMargins": 0.67084,
"operatingMargins": 0.32676,
"profitMargins": 0.25298,
"returnOnEquity": 0.57572,
"returnOnAssets": 0.06335,
"debtToEquity": 415.265,
"currentRatio": 1.347,
"quickRatio": 1.224,
"freeCashflow": -22298499072,
"totalCash": 39132000256,
"totalDebt": 162164998144,
"dividendYield": 0.009399999999999999,
"payoutRatio": 0.35909998,
"beta": 1.655,
"targetMeanPrice": 251.20462,
"targetHighPrice": 400.0,
"targetLowPrice": 155.0,
"recommendationKey": "buy",
"numberOfAnalystOpinions": 39
},
"ADBE": {
"marketCap": 96151101440,
"trailingPE": 13.870555,
"forwardPE": 8.980935,
"pegRatio": 0.71,
"priceToBook": 8.447443,
"enterpriseToEbitda": 10.382,
"revenueGrowth": 0.12,
"earningsGrowth": 0.111,
"earningsQuarterlyGrowth": 0.043,
"grossMargins": 0.89396006,
"operatingMargins": 0.38762,
"profitMargins": 0.29477,
"returnOnEquity": 0.58774,
"returnOnAssets": 0.18905,
"debtToEquity": 58.34,
"currentRatio": 0.912,
"quickRatio": 0.789,
"freeCashflow": 9321374720,
"totalCash": 6898999808,
"totalDebt": 6670000128,
"dividendYield": null,
"payoutRatio": 0.0,
"beta": 1.404,
"targetMeanPrice": 329.80847,
"targetHighPrice": 487.0,
"targetLowPrice": 220.0,
"recommendationKey": "buy",
"numberOfAnalystOpinions": 33
},
"PLTR": {
"marketCap": 316613001216,
"trailingPE": 148.39326,
"forwardPE": 63.670288,
"pegRatio": 1.96,
"priceToBook": 37.466667,
"enterpriseToEbitda": 158.282,
"revenueGrowth": 0.847,
"earningsGrowth": 3.25,
"earningsQuarterlyGrowth": 3.067,
"grossMargins": 0.84073997,
"operatingMargins": 0.46183997,
"profitMargins": 0.43673,
"returnOnEquity": 0.32587,
"returnOnAssets": 0.14702,
"debtToEquity": 2.477,
"currentRatio": 6.907,
"quickRatio": 6.82,
"freeCashflow": 1752997120,
"totalCash": 8026413056,
"totalDebt": 211976992,
"dividendYield": null,
"payoutRatio": 0.0,
"beta": 1.515,
"targetMeanPrice": 183.7289,
"targetHighPrice": 255.0,
"targetLowPrice": 70.0,
"recommendationKey": "buy",
"numberOfAnalystOpinions": 27
},
"ARM": {
"marketCap": 346976059392,
"trailingPE": 373.40228,
"forwardPE": 106.12733,
"pegRatio": 3.01,
"priceToBook": 41.718246,
"enterpriseToEbitda": 344.568,
"revenueGrowth": 0.201,
"earningsGrowth": 0.479,
"earningsQuarterlyGrowth": 0.49,
"grossMargins": 0.97541,
"operatingMargins": 0.2953,
"profitMargins": 0.18374,
"returnOnEquity": 0.119540006,
"returnOnAssets": 0.057800002,
"debtToEquity": 5.926,
"currentRatio": 5.996,
"quickRatio": 5.834,
"freeCashflow": 750499968,
"totalCash": 3600999936,
"totalDebt": 491000000,
"dividendYield": null,
"payoutRatio": 0.0,
"beta": 3.786,
"targetMeanPrice": 254.86542,
"targetHighPrice": 500.0,
"targetLowPrice": 125.0,
"recommendationKey": "buy",
"numberOfAnalystOpinions": 37
},
"DELL": {
"marketCap": 247992172544,
"trailingPE": 30.444977,
"forwardPE": 18.051167,
"pegRatio": 0.66,
"priceToBook": -176.50485,
"enterpriseToEbitda": 20.094,
"revenueGrowth": 0.875,
"earningsGrowth": 2.825,
"earningsQuarterlyGrowth": 2.563,
"grossMargins": 0.19173999,
"operatingMargins": 0.08339,
"profitMargins": 0.062750004,
"returnOnEquity": null,
"returnOnAssets": 0.06944,
"debtToEquity": null,
"currentRatio": 0.946,
"quickRatio": 0.612,
"freeCashflow": -128125000,
"totalCash": 11578000384,
"totalDebt": 31160999936,
"dividendYield": 0.0063,
"payoutRatio": 0.1757,
"beta": 1.378,
"targetMeanPrice": 483.82608,
"targetHighPrice": 700.0,
"targetLowPrice": 213.0,
"recommendationKey": "buy",
"numberOfAnalystOpinions": 23
},
"SMCI": {
"marketCap": 24441647104,
"trailingPE": 21.389473,
"forwardPE": 12.540964,
"pegRatio": 0.91,
"priceToBook": 3.2261648,
"enterpriseToEbitda": 21.729,
"revenueGrowth": 1.227,
"earningsGrowth": 3.26,
"earningsQuarterlyGrowth": 3.444,
"grossMargins": 0.08394,
"operatingMargins": 0.061100002,
"profitMargins": 0.03701,
"returnOnEquity": 0.17877,
"returnOnAssets": 0.05524,
"debtToEquity": 120.798,
"currentRatio": 2.655,
"quickRatio": 1.2,
"freeCashflow": -7448383488,
"totalCash": 1305032960,
"totalDebt": 9151156224,
"dividendYield": null,
"payoutRatio": 0.0,
"beta": 1.869,
"targetMeanPrice": 37.625,
"targetHighPrice": 58.0,
"targetLowPrice": 15.0,
"recommendationKey": "hold",
"numberOfAnalystOpinions": 16
},
"ASML": {
"marketCap": 685183991808,
"trailingPE": 59.797176,
"forwardPE": 37.21795,
"pegRatio": 2.42,
"priceToBook": 1586.2924,
"enterpriseToEbitda": 2947.264,
"revenueGrowth": 0.132,
"earningsGrowth": 0.192,
"earningsQuarterlyGrowth": 0.171,
"grossMargins": 0.52603,
"operatingMargins": 0.36020002,
"profitMargins": 0.29713,
"returnOnEquity": 0.52236,
"returnOnAssets": 0.15664,
"debtToEquity": 12.989,
"currentRatio": 1.36,
"quickRatio": 0.691,
"freeCashflow": 8243274752,
"totalCash": 8376300032,
"totalDebt": 2705600000,
"dividendYield": 0.005,
"payoutRatio": 0.2582,
"beta": 1.396,
"targetMeanPrice": 1697.5917,
"targetHighPrice": 2255.4333,
"targetLowPrice": 893.03937,
"recommendationKey": "strong_buy",
"numberOfAnalystOpinions": 15
},
"LRCX": {
"marketCap": 409136824320,
"trailingPE": 61.844994,
"forwardPE": 41.191944,
"pegRatio": 1.89,
"priceToBook": 38.653122,
"enterpriseToEbitda": 51.573,
"revenueGrowth": 0.238,
"earningsGrowth": 0.408,
"earningsQuarterlyGrowth": 0.372,
"grossMargins": 0.49979,
"operatingMargins": 0.35042998,
"profitMargins": 0.30938998,
"returnOnEquity": 0.66762,
"returnOnAssets": 0.22778,
"debtToEquity": 35.282,
"currentRatio": 2.536,
"quickRatio": 1.695,
"freeCashflow": 4352341504,
"totalCash": 4750936064,
"totalDebt": 3734479104,
"dividendYield": 0.0032,
"payoutRatio": 0.1909,
"beta": 1.868,
"targetMeanPrice": 318.21875,
"targetHighPrice": 385.0,
"targetLowPrice": 220.0,
"recommendationKey": "buy",
"numberOfAnalystOpinions": 32
},
"AMAT": {
"marketCap": 396352487424,
"trailingPE": 46.962368,
"forwardPE": 30.873215,
"pegRatio": 1.54,
"priceToBook": 16.57734,
"enterpriseToEbitda": 42.026,
"revenueGrowth": 0.114,
"earningsGrowth": 0.335,
"earningsQuarterlyGrowth": 0.313,
"grossMargins": 0.48956,
"operatingMargins": 0.31896,
"profitMargins": 0.29314,
"returnOnEquity": 0.39692003,
"returnOnAssets": 0.14858,
"debtToEquity": 30.399,
"currentRatio": 2.508,
"quickRatio": 1.624,
"freeCashflow": 3040375040,
"totalCash": 8240999936,
"totalDebt": 7267999744,
"dividendYield": 0.0043,
"payoutRatio": 0.1731,
"beta": 1.672,
"targetMeanPrice": 511.16666,
"targetHighPrice": 575.0,
"targetLowPrice": 358.0,
"recommendationKey": "strong_buy",
"numberOfAnalystOpinions": 36
},
"KLAC": {
"marketCap": 279460610048,
"trailingPE": 60.777557,
"forwardPE": 42.912045,
"pegRatio": 2.21,
"priceToBook": 47.961487,
"enterpriseToEbitda": 47.273,
"revenueGrowth": 0.115,
"earningsGrowth": 0.118,
"earningsQuarterlyGrowth": 0.103,
"grossMargins": 0.61446,
"operatingMargins": 0.41215,
"profitMargins": 0.35661998,
"returnOnEquity": 0.94975996,
"returnOnAssets": 0.21282,
"debtToEquity": 105.4,
"currentRatio": 3.026,
"quickRatio": 1.963,
"freeCashflow": 2890187008,
"totalCash": 4957938176,
"totalDebt": 6145359872,
"dividendYield": 0.0044,
"payoutRatio": 0.2152,
"beta": 1.504,
"targetMeanPrice": 1869.2759,
"targetHighPrice": 2180.0,
"targetLowPrice": 1500.0,
"recommendationKey": "buy",
"numberOfAnalystOpinions": 29
}
}
}